{"sql":"SELECT * FROM `ucsb`.`directory_people` WHERE (`type` = 'faculty') AND (`lastName` = 'Genova' AND `firstName` = 'Gina');","data":[{"fullName":"Gina Genova","firstName":"Gina","middleName":"L.","lastName":"Genova","type":"faculty","affiliation":"employee","title":"Continuing Lecturer","departments":"WRIT;SUMS","phone":"","email":"genova@writing.ucsb.edu","location":"Girvetz 1325","lastUpdated":"2012-06-19 14:53:48.0"}],"path":"ucsb\/directory.people@(`type`='faculty')@(`lastName`='Genova',`firstName`='Gina').json"}