{"sql":"SELECT * FROM `ucsb`.`directory_people` WHERE (`type` = 'faculty') AND (`lastName` = 'Luyendyk' AND `firstName` = 'Bruce');","data":[{"fullName":"Bruce Luyendyk","firstName":"Bruce","middleName":"P","lastName":"Luyendyk","type":"faculty","affiliation":"employee","title":"Professor Emeritus, Marine Geophysics;Research Professor","departments":"GEOL","phone":"805-893-3009","email":"luyendyk@eri.ucsb.edu","location":"2111 Webb Hall","lastUpdated":"2012-06-19 14:53:48.0"}],"path":"ucsb\/directory.people@(`type`='faculty')@(`lastName`='Luyendyk',`firstName`='Bruce').json"}