{"sql":"SELECT * FROM `ucsb`.`directory_people` WHERE (`type` = 'faculty') AND (`lastName` = 'Herrera sobek' AND `firstName` = 'Maria');","data":[{"fullName":"Maria Herrera Sobek","firstName":"Maria","middleName":"","lastName":"Herrera Sobek","type":"faculty","affiliation":"employee","title":"Associate Vice Chancellor for Diversity, Equity, and Academic Po;Professor","departments":"EXOF;CHST","phone":"805-893-5114","email":"maria.sobek@evc.ucsb.edu","location":"5105 Cheadle","lastUpdated":"2011-12-20 14:18:15.0"}],"path":"ucsb\/directory.people@(`type`='faculty')@(`lastName`='Herrera sobek',`firstName`='Maria').json"}