{"sql":"SELECT * FROM `ucsb`.`directory_people` WHERE (`type` = 'faculty') AND (`lastName` = 'Startz' AND `firstName` = 'Richard');","data":[{"fullName":"Richard Startz","firstName":"Richard","middleName":"","lastName":"Startz","type":"faculty","affiliation":"employee","title":"Professor","departments":"ECON","phone":"805 893-2895","email":"startz@econ.ucsb.edu","location":"3038 North Hall","lastUpdated":"2012-06-19 14:53:48.0"}],"path":"ucsb\/directory.people@(`type`='faculty')@(`lastName`='Startz',`firstName`='Richard').json"}