{"sql":"SELECT * FROM `ucsb`.`directory_people` WHERE (`type` = 'faculty') AND (`lastName` = 'Collins' AND `firstName` = 'Peter');","data":[{"fullName":"Peter Collins","firstName":"Peter","middleName":"M","lastName":"Collins","type":"faculty","affiliation":"employee","title":"Professor, Endocrinology","departments":"EEMB;SUMS","phone":"805-893-4425","email":"collins@lifesci.ucsb.edu","location":"2139, Biological Sciences II","lastUpdated":"2012-06-19 14:53:48.0"}],"path":"ucsb\/directory.people@(`type`='faculty')@(`lastName`='Collins',`firstName`='Peter').json"}