{"sql":"SELECT * FROM `ucsb`.`directory_people` WHERE (`type` = 'faculty') AND (`lastName` = 'Poot-herrera' AND `firstName` = 'Sara');","data":[{"fullName":"Sara Poot-Herrera","firstName":"Sara","middleName":"G","lastName":"Poot-Herrera","type":"faculty","affiliation":"employee","title":"Professor","departments":"SPAN;GERM","phone":"805-893-4054","email":"spooth@spanport.ucsb.edu","location":"4317 Phelps Hall","lastUpdated":"2012-07-01 05:02:30.0"}],"path":"ucsb\/directory.people@(`type`='faculty')@(`lastName`='Poot-herrera',`firstName`='Sara').json"}