{"sql":"SELECT * FROM `ucsb`.`directory_people` WHERE (`type` = 'faculty') AND (`lastName` = 'Chen' AND `firstName` = 'Yali');","data":[{"fullName":"Yali Chen","firstName":"Yali","middleName":"","lastName":"Chen","type":"faculty","affiliation":"employee","title":"Associate Specialist","departments":"GEOG","phone":"805-893-3867","email":"yali@geog.ucsb.edu","location":"Ellison Hall 3625B","lastUpdated":"2012-07-06 10:32:37.0"}],"path":"ucsb\/directory.people@(`type`='faculty')@(`lastName`='Chen',`firstName`='Yali').json"}