{"sql":"SELECT * FROM `ucsb`.`directory_people` WHERE (`type` = 'faculty') AND (`lastName` = 'Quirk' AND `firstName` = 'Matthew');","data":[{"fullName":"Matthew Quirk","firstName":"Matthew","middleName":"P.","lastName":"Quirk","type":"faculty","affiliation":"employee","title":"Assistant Professor","departments":"EDUC","phone":"805-893-5914","email":"mquirk@education.ucsb.edu","location":"2145 Education Building","lastUpdated":"2012-08-16 09:54:24.0"}],"path":"ucsb\/directory.people@(`type`='faculty')@(`lastName`='Quirk',`firstName`='Matthew').json"}