{"sql":"SELECT * FROM `ucsb`.`directory_departments` WHERE (CONCAT(`departmentName`) = 'Computer Science - Letters and Science');","data":[{"departmentName":"Computer Science - Letters and Science","buildingId":"0","college":"ls-intro","chair":"","viceChair":"","programChair":"","associateChair":"","departmentChair":"","director":"","viceDirector":"","programDirector":"","associateDirector":"","executiveDirector":"","location":"Room 2104\r","phone":"(805) 893-4321 ","website":""}],"path":"ucsb\/directory.departments@([`departmentName`]='Computer Science - Letters and Science').json"}